ledge/__about__.py
ledge/__init__.py
ledge/datatypes.py
ledge/fill.py
ledge/merge.py
ledge/update.py
ledge/utils.py
ledge-0.0.8.dist-info/DESCRIPTION.rst
ledge-0.0.8.dist-info/METADATA
ledge-0.0.8.dist-info/RECORD
ledge-0.0.8.dist-info/WHEEL
ledge-0.0.8.dist-info/metadata.json
ledge-0.0.8.dist-info/top_level.txt
