Metadata-Version: 2.0
Name: ledge
Version: 0.0.8
Summary: Hedging algorithms with lag
Home-page: https://github.com/reichlab/ledge
Author: Abhinav Tushar
Author-email: lepisma@fastmail.com
License: GPLv3
Platform: UNKNOWN
Classifier: License :: OSI Approved :: GNU General Public License v3 (GPLv3)
Classifier: Natural Language :: English
Classifier: Programming Language :: Python
Classifier: Programming Language :: Python :: 3 :: Only
Requires-Dist: numpy
Requires-Dist: pandas
Requires-Dist: xarray
